{"kind":"goodUserData","message":"The user data was successfully retrieved.","data":{"name":"RoyalRoppers","ctftimeId":null,"division":"open","score":14613,"globalPlace":11,"divisionPlace":11,"solves":[{"category":"rev","name":"technically-correct","points":492,"solves":19,"id":"technically-correct","createdAt":1708261974669},{"category":"rev","name":"puzzlepalooza","points":489,"solves":26,"id":"puzzlepalooza","createdAt":1708257901300},{"category":"welcome","name":"feedback","points":5,"solves":343,"id":"feedback","createdAt":1708251976557},{"category":"misc","name":"jsfudge","points":486,"solves":31,"id":"jsfudge","createdAt":1708251742866},{"category":"crypto","name":"shuffle","points":484,"solves":35,"id":"shuffle","createdAt":1708214675162},{"category":"misc","name":"remi's-world","points":484,"solves":36,"id":"remis-world","createdAt":1708210416810},{"category":"rev","name":"rbp","points":488,"solves":27,"id":"rbp","createdAt":1708210277401},{"category":"rev","name":"meow meow","points":477,"solves":50,"id":"meow-meow","createdAt":1708204028212},{"category":"misc","name":"my poor git","points":465,"solves":72,"id":"my-poor-git","createdAt":1708199201802},{"category":"crypto","name":"any% ssg","points":489,"solves":25,"id":"any-percent-ssg","createdAt":1708191686874},{"category":"web","name":"ctf-wiki","points":483,"solves":38,"id":"ctf-wiki","createdAt":1708188849007},{"category":"crypto","name":"pprngc","points":485,"solves":33,"id":"pprngc","createdAt":1708183763406},{"category":"misc","name":"discord events","points":472,"solves":60,"id":"discord-events","createdAt":1708181991713},{"category":"pwn","name":"pizza","points":446,"solves":105,"id":"pizza","createdAt":1708179506883},{"category":"rev","name":"flag-finder","points":446,"solves":105,"id":"flag-finder","createdAt":1708179343515},{"category":"misc","name":"mixed signals","points":185,"solves":471,"id":"mixed-signals","createdAt":1708178331656},{"category":"misc","name":"gacha","points":414,"solves":152,"id":"gacha","createdAt":1708177720510},{"category":"web","name":"jason-web-token","points":471,"solves":62,"id":"jason-web-token","createdAt":1708177158013},{"category":"rev","name":"glottem","points":455,"solves":89,"id":"glottem","createdAt":1708176688006},{"category":"pwn","name":"sus","points":426,"solves":136,"id":"sus","createdAt":1708173157585},{"category":"crypto","name":"prove it!","points":482,"solves":41,"id":"prove-it","createdAt":1708172811992},{"category":"web","name":"penguin-login","points":392,"solves":182,"id":"penguin-login","createdAt":1708172591149},{"category":"pwn","name":"52-card-monty","points":379,"solves":200,"id":"52-card-monty","createdAt":1708172338150},{"category":"web","name":"pogn","points":388,"solves":188,"id":"pogn","createdAt":1708167278335},{"category":"pwn","name":"aplet123","points":338,"solves":251,"id":"aplet123","createdAt":1708167217133},{"category":"crypto","name":"very-hot","points":216,"solves":416,"id":"very-hot","createdAt":1708166884665},{"category":"web","name":"new-housing-portal","points":368,"solves":214,"id":"new-housing-portal","createdAt":1708166045000},{"category":"misc","name":"one by one","points":383,"solves":194,"id":"one-by-one","createdAt":1708165902704},{"category":"web","name":"la housing portal","points":265,"solves":344,"id":"la-housing-portal","createdAt":1708164059789},{"category":"rev","name":"shattered-memories","points":115,"solves":697,"id":"shattered-memories","createdAt":1708163532387},{"category":"crypto","name":"budget-bag","points":482,"solves":39,"id":"budget-bag","createdAt":1708162149249},{"category":"misc","name":"infinite loop","points":153,"solves":545,"id":"infinite-loop","createdAt":1708161742080},{"category":"crypto","name":"valentines-day","points":195,"solves":452,"id":"valentines-day","createdAt":1708161283746},{"category":"misc","name":"closed","points":343,"solves":245,"id":"closed","createdAt":1708160530075},{"category":"web","name":"flaglang","points":133,"solves":607,"id":"flaglang","createdAt":1708159290131},{"category":"crypto","name":"hOlyT","points":422,"solves":141,"id":"holyt","createdAt":1708159214824},{"category":"rev","name":"aplet321","points":199,"solves":445,"id":"aplet321","createdAt":1708158631544},{"category":"crypto","name":"selamat pagi","points":275,"solves":331,"id":"selamat-pagi","createdAt":1708158312204},{"category":"web","name":"terms-and-conditions","points":106,"solves":771,"id":"terms-and-conditions","createdAt":1708158170149},{"category":"rev","name":"the-secret-of-java-island","points":312,"solves":284,"id":"the-secret-of-java-island","createdAt":1708158111545},{"category":"welcome","name":"discord","points":15,"solves":777,"id":"discord","createdAt":1708157597058},{"category":"welcome","name":"rules","points":10,"solves":842,"id":"rules","createdAt":1708155077244}],"bloods":[]}}