{"kind":"goodUserData","message":"The user data was successfully retrieved.","data":{"name":"sayonara","ctftimeId":null,"division":"open","score":7140,"globalPlace":61,"divisionPlace":61,"solves":[{"category":"rev","name":"glottem","points":455,"solves":89,"id":"glottem","createdAt":1708279336879},{"category":"web","name":"penguin-login","points":392,"solves":182,"id":"penguin-login","createdAt":1708272279334},{"category":"pwn","name":"pizza","points":446,"solves":105,"id":"pizza","createdAt":1708253160857},{"category":"misc","name":"mixed signals","points":185,"solves":471,"id":"mixed-signals","createdAt":1708252191986},{"category":"rev","name":"the-secret-of-java-island","points":312,"solves":284,"id":"the-secret-of-java-island","createdAt":1708241956356},{"category":"welcome","name":"feedback","points":5,"solves":343,"id":"feedback","createdAt":1708232648349},{"category":"pwn","name":"ppplot","points":491,"solves":20,"id":"ppplot","createdAt":1708207902791},{"category":"misc","name":"gacha","points":414,"solves":152,"id":"gacha","createdAt":1708194758485},{"category":"pwn","name":"sus","points":426,"solves":136,"id":"sus","createdAt":1708189619787},{"category":"misc","name":"infinite loop","points":153,"solves":545,"id":"infinite-loop","createdAt":1708184311185},{"category":"crypto","name":"selamat pagi","points":275,"solves":331,"id":"selamat-pagi","createdAt":1708183860330},{"category":"rev","name":"aplet321","points":199,"solves":445,"id":"aplet321","createdAt":1708182112516},{"category":"crypto","name":"prove it!","points":482,"solves":41,"id":"prove-it","createdAt":1708181614943},{"category":"misc","name":"closed","points":343,"solves":245,"id":"closed","createdAt":1708178571321},{"category":"web","name":"new-housing-portal","points":368,"solves":214,"id":"new-housing-portal","createdAt":1708174065428},{"category":"web","name":"la housing portal","points":265,"solves":344,"id":"la-housing-portal","createdAt":1708171428644},{"category":"crypto","name":"valentines-day","points":195,"solves":452,"id":"valentines-day","createdAt":1708166898501},{"category":"web","name":"flaglang","points":133,"solves":607,"id":"flaglang","createdAt":1708158093659},{"category":"pwn","name":"52-card-monty","points":379,"solves":200,"id":"52-card-monty","createdAt":1708155232351},{"category":"rev","name":"shattered-memories","points":115,"solves":697,"id":"shattered-memories","createdAt":1708151405677},{"category":"pwn","name":"aplet123","points":338,"solves":251,"id":"aplet123","createdAt":1708149923979},{"category":"crypto","name":"hOlyT","points":422,"solves":141,"id":"holyt","createdAt":1708149797550},{"category":"crypto","name":"very-hot","points":216,"solves":416,"id":"very-hot","createdAt":1708142967580},{"category":"web","name":"terms-and-conditions","points":106,"solves":771,"id":"terms-and-conditions","createdAt":1708142941519},{"category":"welcome","name":"discord","points":15,"solves":777,"id":"discord","createdAt":1708142835218},{"category":"welcome","name":"rules","points":10,"solves":842,"id":"rules","createdAt":1708142633596}],"bloods":[]}}