{"kind":"goodUserData","message":"The user data was successfully retrieved.","data":{"name":"YegSecCTF","ctftimeId":null,"division":"open","score":2663,"globalPlace":261,"divisionPlace":254,"solves":[{"category":"rev","name":"aplet321","points":199,"solves":445,"id":"aplet321","createdAt":1708274191610},{"category":"rev","name":"shattered-memories","points":115,"solves":697,"id":"shattered-memories","createdAt":1708271564056},{"category":"misc","name":"infinite loop","points":153,"solves":545,"id":"infinite-loop","createdAt":1708204133516},{"category":"pwn","name":"pizza","points":446,"solves":105,"id":"pizza","createdAt":1708200479395},{"category":"misc","name":"closed","points":343,"solves":245,"id":"closed","createdAt":1708199114737},{"category":"pwn","name":"sus","points":426,"solves":136,"id":"sus","createdAt":1708183952559},{"category":"pwn","name":"52-card-monty","points":379,"solves":200,"id":"52-card-monty","createdAt":1708178609878},{"category":"pwn","name":"aplet123","points":338,"solves":251,"id":"aplet123","createdAt":1708171623760},{"category":"web","name":"flaglang","points":133,"solves":607,"id":"flaglang","createdAt":1708152102568},{"category":"web","name":"terms-and-conditions","points":106,"solves":771,"id":"terms-and-conditions","createdAt":1708151706782},{"category":"welcome","name":"discord","points":15,"solves":777,"id":"discord","createdAt":1708142980302},{"category":"welcome","name":"rules","points":10,"solves":842,"id":"rules","createdAt":1708142558607}],"bloods":[]}}