{"kind":"goodUserData","message":"The user data was successfully retrieved.","data":{"name":"CyberDawgs","ctftimeId":null,"division":"open","score":3440,"globalPlace":192,"divisionPlace":188,"solves":[{"category":"web","name":"penguin-login","points":392,"solves":182,"id":"penguin-login","createdAt":1708290190046},{"category":"rev","name":"glottem","points":455,"solves":89,"id":"glottem","createdAt":1708283466080},{"category":"web","name":"la housing portal","points":265,"solves":344,"id":"la-housing-portal","createdAt":1708223454132},{"category":"web","name":"flaglang","points":133,"solves":607,"id":"flaglang","createdAt":1708191580057},{"category":"misc","name":"one by one","points":383,"solves":194,"id":"one-by-one","createdAt":1708190718678},{"category":"misc","name":"closed","points":343,"solves":245,"id":"closed","createdAt":1708187320146},{"category":"misc","name":"mixed signals","points":185,"solves":471,"id":"mixed-signals","createdAt":1708155913865},{"category":"rev","name":"aplet321","points":199,"solves":445,"id":"aplet321","createdAt":1708153740316},{"category":"crypto","name":"selamat pagi","points":275,"solves":331,"id":"selamat-pagi","createdAt":1708153514945},{"category":"misc","name":"infinite loop","points":153,"solves":545,"id":"infinite-loop","createdAt":1708152482752},{"category":"web","name":"terms-and-conditions","points":106,"solves":771,"id":"terms-and-conditions","createdAt":1708151713194},{"category":"crypto","name":"valentines-day","points":195,"solves":452,"id":"valentines-day","createdAt":1708150485380},{"category":"crypto","name":"very-hot","points":216,"solves":416,"id":"very-hot","createdAt":1708146593676},{"category":"rev","name":"shattered-memories","points":115,"solves":697,"id":"shattered-memories","createdAt":1708143068236},{"category":"welcome","name":"discord","points":15,"solves":777,"id":"discord","createdAt":1708142661685},{"category":"welcome","name":"rules","points":10,"solves":842,"id":"rules","createdAt":1708142607533}],"bloods":[]}}