{"kind":"goodUserData","message":"The user data was successfully retrieved.","data":{"name":"jt","ctftimeId":null,"division":"open","score":1364,"globalPlace":443,"divisionPlace":429,"solves":[{"category":"pwn","name":"flipma","points":492,"solves":19,"id":"flipma","createdAt":1708267813584},{"category":"pwn","name":"pizza","points":446,"solves":105,"id":"pizza","createdAt":1708258487263},{"category":"pwn","name":"sus","points":426,"solves":136,"id":"sus","createdAt":1708247122167}],"bloods":[]}}