{"kind":"goodUserData","message":"The user data was successfully retrieved.","data":{"name":"Cyb3rV3ter4n5","ctftimeId":null,"division":"open","score":4409,"globalPlace":143,"divisionPlace":142,"solves":[{"category":"rev","name":"ctfd-plus","points":384,"solves":173,"id":"ctfd-plus","createdAt":1676144834434},{"category":"pwn","name":"bot","points":363,"solves":197,"id":"bot","createdAt":1676142103952},{"category":"web","name":"uuid hell","points":391,"solves":165,"id":"uuid-hell","createdAt":1676139596713},{"category":"misc","name":"new-challenge","points":425,"solves":123,"id":"new-challenge","createdAt":1676138489003},{"category":"rev","name":"finals-simulator","points":267,"solves":306,"id":"finals-simulator","createdAt":1676138122959},{"category":"misc","name":"EBE","points":183,"solves":426,"id":"ebe","createdAt":1676135057299},{"category":"misc","name":"hike to where?","points":353,"solves":209,"id":"hike-to-where","createdAt":1676134472205},{"category":"rev","name":"string-cheese","points":112,"solves":644,"id":"string-cheese","createdAt":1676133763791},{"category":"misc","name":"hidden in plain sheets","points":315,"solves":251,"id":"hidden-in-plain-sheets","createdAt":1676133550909},{"category":"misc","name":"CATS!","points":107,"solves":683,"id":"cats","createdAt":1676131467382},{"category":"web","name":"metaverse","points":236,"solves":346,"id":"metaverse","createdAt":1676131327715},{"category":"web","name":"college-tour","points":100,"solves":756,"id":"college-tour","createdAt":1676131049883},{"category":"rev","name":"caterpillar","points":200,"solves":398,"id":"caterpillar","createdAt":1676130012691},{"category":"crypto","name":"chinese-lazy-theorem-1","points":238,"solves":343,"id":"chinese-lazy-theorem-1","createdAt":1676129771055},{"category":"crypto","name":"greek cipher","points":254,"solves":323,"id":"greek-cipher","createdAt":1676129390206},{"category":"pwn","name":"gatekeep","points":138,"solves":529,"id":"gatekeep","createdAt":1676127189202},{"category":"crypto","name":"one-more-time-pad","points":154,"solves":486,"id":"one-more-time-pad","createdAt":1676126797267},{"category":"crypto","name":"rolling in the mud","points":179,"solves":434,"id":"rolling-in-the-mud","createdAt":1676126772261},{"category":"misc","name":"discord","points":10,"solves":719,"id":"discord","createdAt":1676126074094}],"bloods":[]}}