{"kind":"goodUserData","message":"The user data was successfully retrieved.","data":{"name":"b2brt","ctftimeId":null,"division":"open","score":140,"globalPlace":897,"divisionPlace":869,"solves":[{"category":"rev","name":"shattered-memories","points":115,"solves":697,"id":"shattered-memories","createdAt":1708192069764},{"category":"welcome","name":"discord","points":15,"solves":777,"id":"discord","createdAt":1708167764150},{"category":"welcome","name":"rules","points":10,"solves":842,"id":"rules","createdAt":1708167685834}],"bloods":[]}}