{"kind":"goodUserData","message":"The user data was successfully retrieved.","data":{"name":"Chromosome Overflow","ctftimeId":null,"division":"open","score":4389,"globalPlace":145,"divisionPlace":143,"solves":[{"category":"misc","name":"EBE","points":183,"solves":426,"id":"ebe","createdAt":1676234756514},{"category":"web","name":"uuid hell","points":391,"solves":165,"id":"uuid-hell","createdAt":1676219786647},{"category":"misc","name":"feedback","points":10,"solves":285,"id":"feedback","createdAt":1676209400287},{"category":"web","name":"metaverse","points":236,"solves":346,"id":"metaverse","createdAt":1676162518053},{"category":"crypto","name":"chinese-lazy-theorem-2","points":391,"solves":165,"id":"chinese-lazy-theorem-2","createdAt":1676149274408},{"category":"misc","name":"hike to where?","points":353,"solves":209,"id":"hike-to-where","createdAt":1676146992508},{"category":"misc","name":"hidden in plain sheets","points":315,"solves":251,"id":"hidden-in-plain-sheets","createdAt":1676146080448},{"category":"misc","name":"discord l34k","points":410,"solves":142,"id":"discord-leak","createdAt":1676138643597},{"category":"crypto","name":"greek cipher","points":254,"solves":323,"id":"greek-cipher","createdAt":1676137315663},{"category":"crypto","name":"rolling in the mud","points":179,"solves":434,"id":"rolling-in-the-mud","createdAt":1676135244668},{"category":"rev","name":"finals-simulator","points":267,"solves":306,"id":"finals-simulator","createdAt":1676130069996},{"category":"pwn","name":"gatekeep","points":138,"solves":529,"id":"gatekeep","createdAt":1676122828959},{"category":"crypto","name":"guess-the-bit!","points":341,"solves":222,"id":"guess-the-bit","createdAt":1676122084942},{"category":"rev","name":"caterpillar","points":200,"solves":398,"id":"caterpillar","createdAt":1676119535680},{"category":"misc","name":"CATS!","points":107,"solves":683,"id":"cats","createdAt":1676115548179},{"category":"rev","name":"string-cheese","points":112,"solves":644,"id":"string-cheese","createdAt":1676113716805},{"category":"crypto","name":"chinese-lazy-theorem-1","points":238,"solves":343,"id":"chinese-lazy-theorem-1","createdAt":1676111317286},{"category":"crypto","name":"one-more-time-pad","points":154,"solves":486,"id":"one-more-time-pad","createdAt":1676110225944},{"category":"misc","name":"discord","points":10,"solves":719,"id":"discord","createdAt":1676109755163},{"category":"web","name":"college-tour","points":100,"solves":756,"id":"college-tour","createdAt":1676098801161}],"bloods":[]}}